ip_helper/library/__init__.py
ip_helper/library/ip_schema.py
ip_helper/library/ipv4.py
ip_helper/library/ipv6.py
ip_helper/main.py
ip_helper-0.1.0.dist-info/METADATA
ip_helper-0.1.0.dist-info/WHEEL
ip_helper-0.1.0.dist-info/entry_points.txt
ip_helper-0.1.0.dist-info/RECORD
