Metadata-Version: 2.1
Name: ip-helper
Version: 0.1.0
Summary: 
Author: Xian Wu
Author-email: xianwuusa@gmail.com
Requires-Python: >=3.11,<4.0
Classifier: Programming Language :: Python :: 3
Classifier: Programming Language :: Python :: 3.11
Classifier: Programming Language :: Python :: 3.12
Requires-Dist: pydantic (>=2.9.2,<3.0.0)
Requires-Dist: pytest (>=8.3.3,<9.0.0)
